[
  {
    "Id": 1,
    "title": "Semana Sin Azúcar Añadida",
    "description": "Evita alimentos con azúcar añadida durante 7 días. Lee etiquetas y elige opciones naturales.",
    "type": "consecutive",
    "target": 7,
    "unit": "días",
    "difficulty": "Medio",
    "pointsReward": 35,
    "duration": 7,
    "startDate": "2024-01-15T00:00:00Z",
    "endDate": "2024-01-21T23:59:59Z",
    "status": "active",
    "participants": 156,
    "createdAt": "2024-01-14T10:00:00Z"
  },
  {
    "Id": 2,
    "title": "Reto Hidratación Plus",
    "description": "Bebe 2.5 litros de agua diariamente durante una semana completa.",
    "type": "incremental",
    "target": 17,
    "unit": "vasos (250ml)",
    "difficulty": "Fácil",
    "pointsReward": 25,
    "duration": 7,
    "startDate": "2024-01-15T00:00:00Z",
    "endDate": "2024-01-21T23:59:59Z",
    "status": "active",
    "participants": 203,
    "createdAt": "2024-01-14T10:00:00Z"
  },
  {
    "Id": 3,
    "title": "Semana Sin Redes Sociales",
    "description": "Desconéctate de redes sociales por 7 días. Enfócate en actividades presenciales.",
    "type": "consecutive",
    "target": 7,
    "unit": "días",
    "difficulty": "Difícil",
    "pointsReward": 50,
    "duration": 7,
    "startDate": "2024-01-15T00:00:00Z",
    "endDate": "2024-01-21T23:59:59Z",
    "status": "active",
    "participants": 89,
    "createdAt": "2024-01-14T10:00:00Z"
  },
  {
    "Id": 4,
    "title": "7 Días de Gratitud",
    "description": "Escribe 3 cosas por las que estás agradecido cada día durante una semana.",
    "type": "incremental",
    "target": 21,
    "unit": "gratitudes",
    "difficulty": "Fácil",
    "pointsReward": 30,
    "duration": 7,
    "startDate": "2024-01-15T00:00:00Z",
    "endDate": "2024-01-21T23:59:59Z",
    "status": "active",
    "participants": 267,
    "createdAt": "2024-01-14T10:00:00Z"
  },
  {
    "Id": 5,
    "title": "Desafío 10,000 Pasos Diarios",
    "description": "Camina mínimo 10,000 pasos cada día durante una semana completa.",
    "type": "incremental",
    "target": 70000,
    "unit": "pasos",
    "difficulty": "Medio",
    "pointsReward": 40,
    "duration": 7,
    "startDate": "2024-01-15T00:00:00Z",
    "endDate": "2024-01-21T23:59:59Z",
    "status": "active",
    "participants": 134,
    "createdAt": "2024-01-14T10:00:00Z"
  },
  {
    "Id": 6,
    "title": "Semana Vegetariana",
    "description": "Come solo alimentos vegetarianos durante 7 días. Descubre nuevas recetas plantas.",
    "type": "consecutive",
    "target": 7,
    "unit": "días",
    "difficulty": "Medio",
    "pointsReward": 35,
    "duration": 7,
    "startDate": "2024-01-22T00:00:00Z",
    "endDate": "2024-01-28T23:59:59Z",
    "status": "upcoming",
    "participants": 0,
    "createdAt": "2024-01-14T10:00:00Z"
  },
  {
    "Id": 7,
    "title": "Reto Lectura: 30 Minutos Diarios",
    "description": "Lee al menos 30 minutos cada día durante una semana. Cualquier tipo de lectura cuenta.",
    "type": "incremental",
    "target": 210,
    "unit": "minutos",
    "difficulty": "Fácil",
    "pointsReward": 25,
    "duration": 7,
    "startDate": "2024-01-22T00:00:00Z",
    "endDate": "2024-01-28T23:59:59Z",
    "status": "upcoming",
    "participants": 0,
    "createdAt": "2024-01-14T10:00:00Z"
  },
  {
    "Id": 8,
    "title": "Semana Sin Comida Chatarra",
    "description": "Evita comida procesada, frituras y snacks poco saludables durante 7 días.",
    "type": "consecutive",
    "target": 7,
    "unit": "días",
    "difficulty": "Medio",
    "pointsReward": 35,
    "duration": 7,
    "startDate": "2024-01-22T00:00:00Z",
    "endDate": "2024-01-28T23:59:59Z",
    "status": "upcoming",
    "participants": 0,
    "createdAt": "2024-01-14T10:00:00Z"
  }
]